Metadata-Version: 2.1
Name: PyMT64
Version: 1.9
Summary: Python version of the Mersenne Twister 64-bit pseudorandom number generator
Home-page: http://lesia.obspm.fr/
Author: R. Samadi
Author-email: reza.samadi@obspm.fr
License: UNKNOWN
Platform: UNKNOWN
